{
  "_class": "shapePath",
  "booleanOperation": -1,
  "do_objectID": "692BF452-E71A-440E-B7B8-2B510FA9479D",
  "edited": true,
  "exportOptions": {
    "_class": "exportOptions",
    "exportFormats": [
    ],
    "includedLayerIds": [
    ],
    "layerOptions": 0,
    "shouldTrim": false
  },
  "frame": {
    "_class": "rect",
    "constrainProportions": false,
    "height": 12.3345338,
    "width": 12.2475123,
    "x": 0,
    "y": 0
  },
  "isFlippedHorizontal": false,
  "isFlippedVertical": false,
  "isLocked": false,
  "isVisible": true,
  "layerListExpandedType": 0,
  "name": "Fill-11-path",
  "nameIsFixed": false,
  "path": {
    "_class": "path",
    "isClosed": false,
    "pointRadiusBehaviour": 1,
    "points": [
      {
        "_class": "curvePoint",
        "cornerRadius": 0,
        "curveFrom": "{0, 0.37661651225115633}",
        "curveMode": 1,
        "curveTo": "{0, 0.37661651225115633}",
        "hasCurveFrom": false,
        "hasCurveTo": false,
        "point": "{0, 0.37661651225115633}"
      },
      {
        "_class": "curvePoint",
        "cornerRadius": 0,
        "curveFrom": "{0.36851359602227135, 0}",
        "curveMode": 1,
        "curveTo": "{0.36851359602227135, 0}",
        "hasCurveFrom": false,
        "hasCurveTo": false,
        "point": "{0.36851359602227135, 0}"
      },
      {
        "_class": "curvePoint",
        "cornerRadius": 0,
        "curveFrom": "{1, 0.62342415406085239}",
        "curveMode": 1,
        "curveTo": "{1, 0.62342415406085239}",
        "hasCurveFrom": false,
        "hasCurveTo": false,
        "point": "{1, 0.62342415406085239}"
      },
      {
        "_class": "curvePoint",
        "cornerRadius": 0,
        "curveFrom": "{0.63144550587632409, 1}",
        "curveMode": 1,
        "curveTo": "{0.63144550587632409, 1}",
        "hasCurveFrom": false,
        "hasCurveTo": false,
        "point": "{0.63144550587632409, 1}"
      },
      {
        "_class": "curvePoint",
        "cornerRadius": 0,
        "curveFrom": "{0, 0.37661651225115633}",
        "curveMode": 1,
        "curveTo": "{0, 0.37661651225115633}",
        "hasCurveFrom": false,
        "hasCurveTo": false,
        "point": "{0, 0.37661651225115633}"
      }
    ]
  },
  "resizingConstraint": 63,
  "resizingType": 0,
  "rotation": 0,
  "shouldBreakMaskChain": false
}