{
  "_class": "group",
  "do_objectID": "97915DFC-071D-408F-8A36-29F125E4960B",
  "exportOptions": {
    "_class": "exportOptions",
    "exportFormats": [
    ],
    "includedLayerIds": [
    ],
    "layerOptions": 0,
    "shouldTrim": false
  },
  "frame": {
    "_class": "rect",
    "constrainProportions": false,
    "height": 104,
    "width": 105,
    "x": 144,
    "y": 252
  },
  "hasClickThrough": false,
  "isFlippedHorizontal": false,
  "isFlippedVertical": false,
  "isLocked": false,
  "isVisible": true,
  "layerListExpandedType": 0,
  "layers": [
    {
      "class": "shapeGroup",
      "id": "4EF63776-88DE-44D5-9461-600EA0590CB1"
    },
    {
      "class": "group",
      "id": "9E08260A-7571-4F50-B365-1F1865B0E803"
    }
  ],
  "name": "video_1",
  "nameIsFixed": true,
  "resizingConstraint": 63,
  "resizingType": 0,
  "rotation": 0,
  "shouldBreakMaskChain": false,
  "style": {
    "_class": "style",
    "endDecorationType": 0,
    "miterLimit": 10,
    "startDecorationType": 0
  }
}